{
  "song_file": "all-hail-the-power",
  "title": "All hail the power of Jesus' name",
  "tune": "CORONATION",
  "meter": "CM extended",
  "stanza_count": "4",
  "composer": "Oliver Holden, 1792",
  "poet": "Edward Perronet, 1780, revised by John Rippon, 1787",
  "key": "G major",
  "date_added": "2021/01/14",
  "tags": [
    "english",
    "christian",
    "4part"
  ],
  "lyrics": "All hail the pow\u2019r of Jesus\u2019 name! Let angels prostrate fall.\nBring forth the royal diadem, and crown him Lord of all.\nBring forth the royal diadem, and crown him Lord of all!\n\nO chosen seed of Israel\u2019s race now ransomed from the fall,\nhail him who saves you by his grace, and crown him Lord of all.\nHail him who saves you by his grace, and crown him Lord of all!\n\nLet ev\u2019ry tongue and ev\u2019ry tribe responsive to his call,\nto him all majesty ascribe, and crown him Lord of all.\nTo him all majesty ascribe, and crown him Lord of all!\n\nOh, that with all the sacred throng we at his feet may fall!\nWe\u2019ll join the everlasting song and crown him Lord of all.\nWe\u2019ll join the everlasting song and crown him Lord of all!\n",
  "image": "https://github.com/kenanbit/hymnsinger/releases/latest/download/all-hail-the-power-trad.png",
  "description": "View, play, and download the PDF sheet music, slideshow, and audio. Lyrics: All hail the pow\u2019r of Jesus\u2019 name! Let angels prostrate fall. Bring forth the royal diadem, and crown him Lord of all. Bring forth the royal diadem, a... english christian 4part",
  "songs_with_same_tune": [
    {
      "t": "CORONATION",
      "s": "Now blessed be the Lord our God"
    }
  ]
}